LICENSE.md
README.md
setup.cfg
setup.py
src/intpolylib/__init__.py
src/intpolylib/poly_base.py
src/intpolylib/poly_dict.py
src/intpolylib/poly_list.py
src/intpolylib/poly_points.py
src/intpolylib/sieve_init.py
src/intpolylib.egg-info/PKG-INFO
src/intpolylib.egg-info/SOURCES.txt
src/intpolylib.egg-info/dependency_links.txt
src/intpolylib.egg-info/requires.txt
src/intpolylib.egg-info/top_level.txt