Metadata-Version: 2.1
Name: intpolylib
Version: 0.2.1
Summary: UNKNOWN
Home-page: https://github.com/Kerad20/polylib
Author: Dariusz Libecki
Author-email: dariuszlibecki@gmail.com
License: MIT
Keywords: polynomials
Platform: UNKNOWN
License-File: LICENSE.md
